openperplex/__init__.py
openperplex/openperplex.py
openperplex-0.2.2.dist-info/METADATA
openperplex-0.2.2.dist-info/WHEEL
openperplex-0.2.2.dist-info/top_level.txt
openperplex-0.2.2.dist-info/RECORD
