Metadata-Version: 2.1
Name: openperplex
Version: 0.2.2
Summary: A Python client for the Openperplex API
Home-page: https://github.com/YassKhazzan/openperplex_python_library
Author: Yassine khazzan
Author-email: Yassine khazzan <yassine.khazzan@gmail.com>
Project-URL: Homepage, https://github.com/YassKhazzan/openperplex_python_library
Classifier: Development Status :: 3 - Alpha
Classifier: Intended Audience :: Developers
Classifier: License :: OSI Approved :: MIT License
Classifier: Operating System :: OS Independent
Classifier: Programming Language :: Python :: 3.8
Classifier: Programming Language :: Python :: 3.9
Classifier: Programming Language :: Python :: 3.10
Classifier: Programming Language :: Python :: 3.11
Classifier: Programming Language :: Python :: 3.12
Requires-Python: >=3.8
Requires-Dist: httpx>=0.26.0
